odoo/addons/product_standard_margin_security/README.rst
odoo/addons/product_standard_margin_security/__init__.py
odoo/addons/product_standard_margin_security/__manifest__.py
odoo/addons/product_standard_margin_security/i18n/it.po
odoo/addons/product_standard_margin_security/i18n/product_standard_margin_security.pot
odoo/addons/product_standard_margin_security/models/__init__.py
odoo/addons/product_standard_margin_security/models/product_product.py
odoo/addons/product_standard_margin_security/models/product_template.py
odoo/addons/product_standard_margin_security/readme/CONTRIBUTORS.md
odoo/addons/product_standard_margin_security/readme/DESCRIPTION.md
odoo/addons/product_standard_margin_security/static/description/icon.png
odoo/addons/product_standard_margin_security/static/description/index.html
odoo_addon_product_standard_margin_security-18.0.1.0.0.2.dist-info/METADATA
odoo_addon_product_standard_margin_security-18.0.1.0.0.2.dist-info/WHEEL
odoo_addon_product_standard_margin_security-18.0.1.0.0.2.dist-info/top_level.txt
odoo_addon_product_standard_margin_security-18.0.1.0.0.2.dist-info/RECORD
